calango/__init__.py
calango/devices.py
calango/media.py
calango/settings.py
calango/utils.py
tests/__init__.py
calango-2.2.8.dist-info/LICENSE
calango-2.2.8.dist-info/METADATA
calango-2.2.8.dist-info/WHEEL
calango-2.2.8.dist-info/top_level.txt
calango-2.2.8.dist-info/RECORD
