Metadata-Version: 2.1
Name: calango
Version: 2.2.8
Summary: It looks like calango
Home-page: https://github.com/cereja-project/calango
Author: Joab Leite
Author-email: jlsn1@ifal.edu.br
Classifier: Programming Language :: Python :: 3
Classifier: License :: OSI Approved :: MIT License
Classifier: Operating System :: OS Independent
Requires-Python: >=3.6
License-File: LICENSE
Requires-Dist: cereja
Requires-Dist: opencv-python
Requires-Dist: matplotlib
Requires-Dist: numpy
